{
  "user": [
    {
      "name": "poonam Bha",
      "mobile": 989898989,
      "pancard": "",
      "email": "poonambhapkar34@gmail.com",
      "pass": "",
      "confirmPass": "",
      "city": "Mumbai",
      "id": 1
    },
    {
      "name": "poonam Bha",
      "mobile": 989898989,
      "pancard": "",
      "email": "poonambhapkar34@gmail.com",
      "pass": "",
      "confirmPass": "",
      "city": "Mumbai",
      "id": 2
    },
    {
      "name": "poonam Bha",
      "mobile": 989898989,
      "pancard": "",
      "email": "poonambhapkar34@gmail.com",
      "pass": "",
      "confirmPass": "",
      "city": "Mumbai",
      "id": 3
    },
    {
      "name": "poonam Bha",
      "mobile": 989898989,
      "pancard": "",
      "email": "poonambhapkar34@gmail.com",
      "pass": "",
      "confirmPass": "",
      "city": "Mumbai",
      "id": 4
    },
    {
      "name": "Abhijit",
      "mobile": 989898989,
      "pancard": "",
      "email": "",
      "pass": "",
      "confirmPass": "",
      "city": "Mumbai",
      "id": 5
    },
    {
      "name": "Abhijit",
      "mobile": 989898989,
      "pancard": "",
      "email": "",
      "pass": "",
      "confirmPass": "",
      "city": "Mumbai",
      "id": 6
    },
    {
      "name": "Abhijit",
      "mobile": 989898989,
      "pancard": "",
      "email": "",
      "pass": "",
      "confirmPass": "",
      "city": "Mumbai",
      "id": 7
    },
    {
      "name": "Abhijit",
      "mobile": 989898989,
      "pancard": "",
      "email": "",
      "pass": "",
      "confirmPass": "",
      "city": "Mumbai",
      "id": 8
    },
    {
      "name": "poonam Bha",
      "mobile": 989898989,
      "pancard": "",
      "email": "poonambhapkar34@gmail.com",
      "pass": "",
      "confirmPass": "",
      "city": "Mumbai",
      "id": 9
    }
  ],
  "admin": [],
  "owner": []
}